twitterbeat
django_twitterstream
