Metadata-Version: 1.0
Name: twitterbeat
Version: 0.9.1
Summary: A library for follow one user from twitter with daemon mode.
Home-page: https://github.com/valdergallo/twitterbeat
Author: valdergallo
Author-email: valdergallo@gmail.com
License: MIT
Keywords: python django twitter follow subprocess daemon
Platform: UNKNOWN
Classifier: Framework :: Django
Classifier: Operating System :: OS Independent
Classifier: Topic :: Software Development
